anahiepro/__init__.py
anahiepro/constants.py
anahiepro/nodes.py
anahiepro/pairwise.py
anahiepro/models/__init__.py
anahiepro/models/_model_builder.py
anahiepro/models/model.py
anahiepro/models/vary_depth_model.py
anahiepro/models/_criterias_builders/__init__.py
anahiepro/models/_criterias_builders/_base_criteria_builder.py
anahiepro/models/_criterias_builders/_empty_criteria_builder.py
anahiepro/models/_criterias_builders/_list_criteria_builder.py
anahiepro/models/_criterias_builders/_list_dict_ctiteria_builder.py
anahiepro/models/_criterias_builders/_wrapper_criteria_builder.py
AnaHiePro-0.0.0.1.dist-info/LICENSE
AnaHiePro-0.0.0.1.dist-info/METADATA
AnaHiePro-0.0.0.1.dist-info/WHEEL
AnaHiePro-0.0.0.1.dist-info/top_level.txt
AnaHiePro-0.0.0.1.dist-info/RECORD
