Metadata-Version: 2.1
Name: AnaHiePro
Version: 0.0.0.1
Summary: "AnaHiePro" is a module that allows solving various tasks of systems analysis using the Analytic Hierarchy Process (AHP).
Home-page: https://github.com/danylevych/AnaHiePro
Author: Oleh Danylevych
Author-email: danylevych123@gmail.com
Classifier: Programming Language :: Python :: 3
Classifier: License :: OSI Approved :: MIT License
Classifier: Operating System :: OS Independent
Requires-Python: >=3.6
License-File: LICENSE
Requires-Dist: numpy
